bugsnag_agent/__init__.py
bugsnag_agent-1.3.0.dist-info/LICENSE.MIT
bugsnag_agent-1.3.0.dist-info/METADATA
bugsnag_agent-1.3.0.dist-info/WHEEL
bugsnag_agent-1.3.0.dist-info/entry_points.txt
bugsnag_agent-1.3.0.dist-info/top_level.txt
bugsnag_agent-1.3.0.dist-info/RECORD
